ombt_orchestrator-1.1.1.dist-info/LICENSE.txt
ombt_orchestrator-1.1.1.dist-info/METADATA
ombt_orchestrator-1.1.1.dist-info/RECORD
ombt_orchestrator-1.1.1.dist-info/WHEEL
ombt_orchestrator-1.1.1.dist-info/entry_points.txt
ombt_orchestrator-1.1.1.dist-info/top_level.txt
orchestrator/__init__.py
orchestrator/campaign.py
orchestrator/cli.py
orchestrator/constants.py
orchestrator/ombt.py
orchestrator/qpid_dispatchgen.py
orchestrator/tasks.py
orchestrator/ansible/ombt.yml
orchestrator/ansible/site.yml
orchestrator/ansible/test_case.yml
orchestrator/ansible/group_vars/all
orchestrator/ansible/roles/chrony/tasks/backup.yml
orchestrator/ansible/roles/chrony/tasks/deploy.yml
orchestrator/ansible/roles/chrony/tasks/destroy.yml
orchestrator/ansible/roles/chrony/tasks/main.yml
orchestrator/ansible/roles/chrony/templates/chrony.conf.j2
orchestrator/ansible/roles/common/tasks/backup.yml
orchestrator/ansible/roles/common/tasks/deploy.yml
orchestrator/ansible/roles/common/tasks/destroy.yml
orchestrator/ansible/roles/common/tasks/main.yml
orchestrator/ansible/roles/grafana/defaults/main.yml
orchestrator/ansible/roles/grafana/tasks/backup.yml
orchestrator/ansible/roles/grafana/tasks/deploy.yml
orchestrator/ansible/roles/grafana/tasks/destroy.yml
orchestrator/ansible/roles/grafana/tasks/main.yml
orchestrator/ansible/roles/influxdb/files/influxdb.conf
orchestrator/ansible/roles/influxdb/files/types.db
orchestrator/ansible/roles/influxdb/tasks/backup.yml
orchestrator/ansible/roles/influxdb/tasks/deploy.yml
orchestrator/ansible/roles/influxdb/tasks/destroy.yml
orchestrator/ansible/roles/influxdb/tasks/main.yml
orchestrator/ansible/roles/ombt/defaults/main.yml
orchestrator/ansible/roles/ombt/tasks/backup.yml
orchestrator/ansible/roles/ombt/tasks/deploy.yml
orchestrator/ansible/roles/ombt/tasks/destroy.yml
orchestrator/ansible/roles/ombt/tasks/main.yml
orchestrator/ansible/roles/ombt/tasks/backup/controller.yml
orchestrator/ansible/roles/ombt/tasks/backup/rpc-client.yml
orchestrator/ansible/roles/ombt/tasks/backup/rpc-server.yml
orchestrator/ansible/roles/ombt/tasks/deploy/controller.yml
orchestrator/ansible/roles/ombt/tasks/deploy/rpc-client.yml
orchestrator/ansible/roles/ombt/tasks/deploy/rpc-server.yml
