Metadata-Version: 2.1
Name: ombt-orchestrator
Version: 1.1.1
Summary: Oslo messaging benchmarking orchestrator
Home-page: https://github.com/msimonin/ombt-orchestrator/
Author: Matthieu Simonin
Author-email: matthieu.simonin@inria.fr
License: UNKNOWN
Project-URL: Source, https://github.com/msimonin/ombt-orchestrator/
Project-URL: Bug Reports, https://github.com/msimonin/ombt-orchestrator/issues
Keywords: benchmark,oslo messaging,RPC
Platform: UNKNOWN
Classifier: Development Status :: 4 - Beta
Classifier: Environment :: Console
Classifier: Intended Audience :: Developers
Classifier: Intended Audience :: Information Technology
Classifier: Intended Audience :: Science/Research
Classifier: Topic :: Scientific/Engineering
Classifier: Topic :: Software Development :: Libraries :: Application Frameworks
Classifier: Topic :: System :: Networking
Classifier: License :: OSI Approved :: GNU General Public License v3 (GPLv3)
Classifier: Operating System :: POSIX :: Linux
Classifier: Programming Language :: Python
Requires-Dist: PyYAML
Requires-Dist: networkx (==2.1)
Requires-Dist: click (<7,>=6.7)
Requires-Dist: enoslib (>=1.4.0)
Requires-Dist: pathlib2; python_version < "3"
